catgram/__init__.py
catgram/category_tree.py
catgram/ccg/__init__.py
catgram/ccg/candc_ignore.py
catgram/ccg/dependencies.py
catgram/ccg/heads.py
catgram/cli/__init__.py
catgram/cli/ccg_depeval.py
catgram/cli/ccg_roots.py
catgram/term_graph.py
catgram-0.3.0.dist-info/LICENSE
catgram-0.3.0.dist-info/METADATA
catgram-0.3.0.dist-info/WHEEL
catgram-0.3.0.dist-info/entry_points.txt
catgram-0.3.0.dist-info/RECORD
