Metadata-Version: 2.1
Name: catgram
Version: 0.3.0
Summary: Basic tools for working with categorial grammars
Home-page: https://github.com/rightaditya/catgram
License: Apache-2.0
Author: Aditya Bhargava
Author-email: aditya@cs.toronto.edu
Requires-Python: >=3.10,<4.0
Classifier: License :: OSI Approved :: Apache Software License
Classifier: Operating System :: OS Independent
Classifier: Programming Language :: Python :: 3
Classifier: Programming Language :: Python :: 3.10
Classifier: Programming Language :: Python :: 3.11
Classifier: Programming Language :: Python :: 3.12
Classifier: Topic :: Scientific/Engineering :: Artificial Intelligence
Classifier: Topic :: Text Processing :: Linguistic
Requires-Dist: lambda-calculus (>=3.0.0,<4.0.0)
Project-URL: Repository, https://github.com/rightaditya/catgram
